{
    "video_info": {
        "title": "Test",
        "output_file": "final_render.mp4",
        "generated_at": "2025-06-15 19:32:59"
    },
    "segments": [
        {
            "start_time": 0.0,
            "end_time": 5.0,
            "type": "celebrity_overlay",
            "celebrity": "Meghan Markle",
            "media": {
                "folder": "/Users/superman/Desktop/Celebrity Folder/Meghan Markle",
                "type": "video",
                "duration": 5.0,
                "file": "21.mp4"
            },
            "transcription_context": [
                "[Description placeholder]"
            ]
        },
        {
            "start_time": 5.0,
            "end_time": 7.0,
            "type": "celebrity_overlay",
            "celebrity": "Meghan Markle",
            "media": {
                "folder": "/Users/superman/Desktop/Celebrity Folder/Meghan Markle",
                "type": "video",
                "duration": 2.0,
                "file": "31.mp4"
            },
            "transcription_context": [
                "[Description placeholder]"
            ]
        },
        {
            "start_time": 7.0,
            "end_time": 10.0,
            "type": "celebrity_overlay",
            "celebrity": "Prince Harry",
            "media": {
                "folder": "/Users/superman/Desktop/Celebrity Folder/Prince Harry",
                "type": "video",
                "duration": 3.0,
                "file": "2.mp4"
            },
            "transcription_context": [
                "[Description placeholder]"
            ]
        },
        {
            "start_time": 10.0,
            "end_time": 15.0,
            "type": "celebrity_overlay",
            "celebrity": "Meghan Markle",
            "media": {
                "folder": "/Users/superman/Desktop/Celebrity Folder/Meghan Markle",
                "type": "video",
                "duration": 5.0,
                "file": "fghgvcb.mp4"
            },
            "transcription_context": [
                "[Description placeholder]"
            ]
        },
        {
            "start_time": 15.0,
            "end_time": 18.0,
            "type": "celebrity_overlay",
            "celebrity": "Meghan Markle",
            "media": {
                "folder": "/Users/superman/Desktop/Celebrity Folder/Meghan Markle",
                "type": "image",
                "duration": 3.0,
                "file": "meghan-markle-the-wider-earth-gala-performance-london-052725-50d8f34a23434e36b46f06e4cfb7b6f6.remini-enhanced.jpg"
            },
            "transcription_context": [
                "[Description placeholder]"
            ]
        },
        {
            "start_time": 18.0,
            "end_time": 22.0,
            "type": "celebrity_overlay",
            "celebrity": "Oprah",
            "media": {
                "folder": "/Users/superman/Desktop/Celebrity Folder/Oprah",
                "type": "video",
                "duration": 4.0,
                "file": "6.mp4"
            },
            "transcription_context": [
                "[Description placeholder]"
            ]
        },
        {
            "start_time": 22.0,
            "end_time": 24.0,
            "type": "celebrity_overlay",
            "celebrity": "Oprah",
            "media": {
                "folder": "/Users/superman/Desktop/Celebrity Folder/Oprah",
                "type": "video",
                "duration": 2.0,
                "file": "23.mp4"
            },
            "transcription_context": [
                "[Description placeholder]"
            ]
        },
        {
            "start_time": 24.0,
            "end_time": 29.0,
            "type": "celebrity_overlay",
            "celebrity": "Meghan Markle",
            "media": {
                "folder": "/Users/superman/Desktop/Celebrity Folder/Meghan Markle",
                "type": "video",
                "duration": 5.0,
                "file": "asd_chf3_rhea1.mp4"
            },
            "transcription_context": [
                "[Description placeholder]"
            ]
        },
        {
            "start_time": 29.0,
            "end_time": 34.0,
            "type": "celebrity_overlay",
            "celebrity": "Meghan Markle",
            "media": {
                "folder": "/Users/superman/Desktop/Celebrity Folder/Meghan Markle",
                "type": "video",
                "duration": 5.0,
                "file": "xcvcxvcx.mp4"
            },
            "transcription_context": [
                "[Description placeholder]"
            ]
        },
        {
            "start_time": 34.0,
            "end_time": 36.0,
            "type": "celebrity_overlay",
            "celebrity": "Meghan Markle",
            "media": {
                "folder": "/Users/superman/Desktop/Celebrity Folder/Meghan Markle",
                "type": "video",
                "duration": 2.0,
                "file": "xcx.mp4"
            },
            "transcription_context": [
                "[Description placeholder]"
            ]
        },
        {
            "start_time": 36.0,
            "end_time": 41.0,
            "type": "celebrity_overlay",
            "celebrity": "South Park",
            "media": {
                "folder": "/Users/superman/Desktop/Celebrity Folder/South Park",
                "type": "video",
                "duration": 5.0,
                "file": "15.mp4"
            },
            "transcription_context": [
                "[Description placeholder]"
            ]
        },
        {
            "start_time": 41.0,
            "end_time": 43.0,
            "type": "celebrity_overlay",
            "celebrity": "South Park",
            "media": {
                "folder": "/Users/superman/Desktop/Celebrity Folder/South Park",
                "type": "video",
                "duration": 2.0,
                "file": "7.mp4"
            },
            "transcription_context": [
                "[Description placeholder]"
            ]
        },
        {
            "start_time": 43.0,
            "end_time": 48.0,
            "type": "celebrity_overlay",
            "celebrity": "Prince Harry",
            "media": {
                "folder": "/Users/superman/Desktop/Celebrity Folder/Prince Harry",
                "type": "video",
                "duration": 5.0,
                "file": "8.mp4"
            },
            "transcription_context": [
                "[Description placeholder]"
            ]
        },
        {
            "start_time": 48.0,
            "end_time": 53.0,
            "type": "celebrity_overlay",
            "celebrity": "Prince Harry",
            "media": {
                "folder": "/Users/superman/Desktop/Celebrity Folder/Prince Harry",
                "type": "video",
                "duration": 5.0,
                "file": "clip_14.mp4"
            },
            "transcription_context": [
                "[Description placeholder]"
            ]
        },
        {
            "start_time": 53.0,
            "end_time": 55.0,
            "type": "celebrity_overlay",
            "celebrity": "Prince Harry",
            "media": {
                "folder": "/Users/superman/Desktop/Celebrity Folder/Prince Harry",
                "type": "image",
                "duration": 2.0,
                "file": "0c93b630-242d-11ef-80de-01d4152f54e3.remini-enhanced.jpg"
            },
            "transcription_context": [
                "[Description placeholder]"
            ]
        },
        {
            "start_time": 55.0,
            "end_time": 57.0,
            "type": "celebrity_overlay",
            "celebrity": "Beyonce",
            "media": {
                "folder": "/Users/superman/Desktop/Celebrity Folder/Beyonce",
                "type": "video",
                "duration": 2.0,
                "file": "48.mp4"
            },
            "transcription_context": [
                "[Description placeholder]"
            ]
        },
        {
            "start_time": 57.0,
            "end_time": 62.0,
            "type": "celebrity_overlay",
            "celebrity": "Oprah",
            "media": {
                "folder": "/Users/superman/Desktop/Celebrity Folder/Oprah",
                "type": "video",
                "duration": 5.0,
                "file": "2.mp4"
            },
            "transcription_context": [
                "[Description placeholder]"
            ]
        },
        {
            "start_time": 62.0,
            "end_time": 65.0,
            "type": "celebrity_overlay",
            "celebrity": "Oprah",
            "media": {
                "folder": "/Users/superman/Desktop/Celebrity Folder/Oprah",
                "type": "image",
                "duration": 3.0,
                "file": "201602-omag-wikfs-949x534.remini-enhanced.jpg"
            },
            "transcription_context": [
                "[Description placeholder]"
            ]
        },
        {
            "start_time": 65.0,
            "end_time": 69.0,
            "type": "celebrity_overlay",
            "celebrity": "Meghan Markle",
            "media": {
                "folder": "/Users/superman/Desktop/Celebrity Folder/Meghan Markle",
                "type": "image",
                "duration": 4.0,
                "file": "602551_6488787_updates.remini-enhanced.jpg"
            },
            "transcription_context": [
                "[Description placeholder]"
            ]
        },
        {
            "start_time": 69.0,
            "end_time": 70.0,
            "type": "celebrity_overlay",
            "celebrity": "Piers Morgan",
            "media": {
                "folder": "/Users/superman/Desktop/Celebrity Folder/Piers Morgan",
                "type": "video",
                "duration": 1.0,
                "file": "3.mp4"
            },
            "transcription_context": [
                "[Description placeholder]"
            ]
        },
        {
            "start_time": 70.0,
            "end_time": 75.0,
            "type": "celebrity_overlay",
            "celebrity": "Meghan Markle",
            "media": {
                "folder": "/Users/superman/Desktop/Celebrity Folder/Meghan Markle",
                "type": "video",
                "duration": 5.0,
                "file": "30.mp4"
            },
            "transcription_context": [
                "[Description placeholder]"
            ]
        },
        {
            "start_time": 75.0,
            "end_time": 78.0,
            "type": "celebrity_overlay",
            "celebrity": "Meghan Markle",
            "media": {
                "folder": "/Users/superman/Desktop/Celebrity Folder/Meghan Markle",
                "type": "video",
                "duration": 3.0,
                "file": "8.mp4"
            },
            "transcription_context": [
                "[Description placeholder]"
            ]
        },
        {
            "start_time": 78.0,
            "end_time": 83.0,
            "type": "celebrity_overlay",
            "celebrity": "Oprah",
            "media": {
                "folder": "/Users/superman/Desktop/Celebrity Folder/Oprah",
                "type": "video",
                "duration": 5.0,
                "file": "28.mp4"
            },
            "transcription_context": [
                "[Description placeholder]"
            ]
        },
        {
            "start_time": 83.0,
            "end_time": 88.0,
            "type": "celebrity_overlay",
            "celebrity": "Martha Stewart",
            "media": {
                "folder": "/Users/superman/Desktop/Celebrity Folder/Martha Stewart",
                "type": "video",
                "duration": 5.0,
                "file": "clip_02_04_Kelly Clarkson Can't Believe Martha Stewart Has Never Ordered Food Delivery_214102.mp4"
            },
            "transcription_context": [
                "[Description placeholder]"
            ]
        },
        {
            "start_time": 88.0,
            "end_time": 93.0,
            "type": "celebrity_overlay",
            "celebrity": "Martha Stewart",
            "media": {
                "folder": "/Users/superman/Desktop/Celebrity Folder/Martha Stewart",
                "type": "video",
                "duration": 5.0,
                "file": "clip_12_02_Martha Stewart Spills on Her Kardashian House Tour and Her Crush on Brad Pitt _ The Tonight Show_215010.mp4"
            },
            "transcription_context": [
                "[Description placeholder]"
            ]
        },
        {
            "start_time": 93.0,
            "end_time": 95.0,
            "type": "celebrity_overlay",
            "celebrity": "Kevin Hart",
            "media": {
                "folder": "/Users/superman/Desktop/Celebrity Folder/Kevin Hart",
                "type": "video",
                "duration": 2.0,
                "file": "1.mp4"
            },
            "transcription_context": [
                "[Description placeholder]"
            ]
        },
        {
            "start_time": 95.0,
            "end_time": 100.0,
            "type": "celebrity_overlay",
            "celebrity": "Meghan Markle",
            "media": {
                "folder": "/Users/superman/Desktop/Celebrity Folder/Meghan Markle",
                "type": "video",
                "duration": 5.0,
                "file": "4.mp4"
            },
            "transcription_context": [
                "[Description placeholder]"
            ]
        },
        {
            "start_time": 100.0,
            "end_time": 104.0,
            "type": "celebrity_overlay",
            "celebrity": "Meghan Markle",
            "media": {
                "folder": "/Users/superman/Desktop/Celebrity Folder/Meghan Markle",
                "type": "image",
                "duration": 4.0,
                "file": "COLOMBIA-BRITAIN-ROYALS-VISIT-3_1728908365907_1732645154372.remini-enhanced.jpg"
            },
            "transcription_context": [
                "[Description placeholder]"
            ]
        },
        {
            "start_time": 104.0,
            "end_time": 109.0,
            "type": "celebrity_overlay",
            "celebrity": "Meghan Markle",
            "media": {
                "folder": "/Users/superman/Desktop/Celebrity Folder/Meghan Markle",
                "type": "video",
                "duration": 5.0,
                "file": "zvz.mp4"
            },
            "transcription_context": [
                "[Description placeholder]"
            ]
        }
    ]
}